CHANGES.rst
CONTRIBUTORS.rst
DEVELOP.rst
LICENSE.GPL
LICENSE.rst
MANIFEST.in
README.rst
setup.cfg
setup.py
docs/index.rst
src/iaweb/__init__.py
src/iaweb.privacy.egg-info/PKG-INFO
src/iaweb.privacy.egg-info/SOURCES.txt
src/iaweb.privacy.egg-info/dependency_links.txt
src/iaweb.privacy.egg-info/entry_points.txt
src/iaweb.privacy.egg-info/namespace_packages.txt
src/iaweb.privacy.egg-info/not-zip-safe
src/iaweb.privacy.egg-info/requires.txt
src/iaweb.privacy.egg-info/top_level.txt
src/iaweb/privacy/__init__.py
src/iaweb/privacy/configure.zcml
src/iaweb/privacy/interfaces.py
src/iaweb/privacy/setuphandlers.py
src/iaweb/privacy/testing.py
src/iaweb/privacy/upgrades.py
src/iaweb/privacy/upgrades.zcml
src/iaweb/privacy/browser/__init__.py
src/iaweb/privacy/browser/configure.zcml
src/iaweb/privacy/browser/overrides/.gitkeep
src/iaweb/privacy/browser/static/.gitkeep
src/iaweb/privacy/locales/__init__.py
src/iaweb/privacy/locales/collective.privacy.pot
src/iaweb/privacy/locales/iaweb.privacy.pot
src/iaweb/privacy/locales/update.sh
src/iaweb/privacy/locales/de/LC_MESSAGES/collective.privacy.po
src/iaweb/privacy/locales/de/LC_MESSAGES/iaweb.privacy.po
src/iaweb/privacy/locales/en/LC_MESSAGES/collective.privacy.po
src/iaweb/privacy/locales/en/LC_MESSAGES/iaweb.privacy.po
src/iaweb/privacy/locales/fr/LC_MESSAGES/collective.privacy.po
src/iaweb/privacy/locales/fr/LC_MESSAGES/iaweb.privacy.po
src/iaweb/privacy/locales/nl/LC_MESSAGES/collective.privacy.po
src/iaweb/privacy/locales/nl/LC_MESSAGES/iaweb.privacy.po
src/iaweb/privacy/profiles/default/browserlayer.xml
src/iaweb/privacy/profiles/default/metadata.xml
src/iaweb/privacy/profiles/default/registry.xml
src/iaweb/privacy/profiles/uninstall/browserlayer.xml
src/iaweb/privacy/rules/__init__.py
src/iaweb/privacy/rules/all.zcml
src/iaweb/privacy/rules/analytics.zcml
src/iaweb/privacy/rules/embed.zcml
src/iaweb/privacy/rules/media.zcml
src/iaweb/privacy/rules/minimal.zcml
src/iaweb/privacy/rules/multilingual.zcml
src/iaweb/privacy/rules/social.zcml
src/iaweb/privacy/tests/__init__.py
src/iaweb/privacy/tests/test_setup.py