Metadata-Version: 2.1
Name: iaweb.privacy
Version: 1.0a2
Summary: Privacy rules for IMIO web projects
Home-page: https://pypi.python.org/pypi/iaweb.privacy
Author: Martin Peeters
Author-email: support@imio.be
License: GPL version 2
Keywords: Python Plone
Platform: UNKNOWN
Classifier: Environment :: Web Environment
Classifier: Framework :: Plone
Classifier: Framework :: Plone :: 4.3
Classifier: Programming Language :: Python
Classifier: Programming Language :: Python :: 2.7
Classifier: Operating System :: OS Independent
Classifier: License :: OSI Approved :: GNU General Public License v2 (GPLv2)
Provides-Extra: test
License-File: LICENSE.GPL
License-File: LICENSE.rst
